fuel_track/__init__.py
fuel_track/app.py
fuel_track/main.py
fuel_track/utils.py
fuel_track-0.0.1.dist-info/LICENCE
fuel_track-0.0.1.dist-info/METADATA
fuel_track-0.0.1.dist-info/WHEEL
fuel_track-0.0.1.dist-info/top_level.txt
fuel_track-0.0.1.dist-info/RECORD
