Metadata-Version: 2.1
Name: fuel_track
Version: 0.0.1
Summary: Lleva seguimiento del consumo de combustible
Author: Juan David Moreno
Author-email: <jmorenoar@unal.edu.co>
Keywords: python,video,stream,video stream,camera stream,sockets
Classifier: Development Status :: 1 - Planning
Classifier: Intended Audience :: Developers
Classifier: Programming Language :: Python :: 3
Classifier: Operating System :: Unix
Classifier: Operating System :: MacOS :: MacOS X
Classifier: Operating System :: Microsoft :: Windows
License-File: LICENCE
Requires-Dist: altgraph ==0.17.4
Requires-Dist: certifi ==2024.2.2
Requires-Dist: charset-normalizer ==3.3.2
Requires-Dist: click ==8.1.7
Requires-Dist: colorama ==0.4.6
Requires-Dist: customtkinter ==5.2.2
Requires-Dist: cx-Logging ==3.2.0
Requires-Dist: darkdetect ==0.8.0
Requires-Dist: decorator ==5.1.1
Requires-Dist: future ==1.0.0
Requires-Dist: geocoder ==1.38.1
Requires-Dist: geographiclib ==2.0
Requires-Dist: geopy ==2.4.1
Requires-Dist: idna ==3.6
Requires-Dist: lief ==0.14.1
Requires-Dist: packaging ==24.0
Requires-Dist: pefile ==2023.2.7
Requires-Dist: pillow ==10.2.0
Requires-Dist: pyinstaller-hooks-contrib ==2024.3
Requires-Dist: pyperclip ==1.8.2
Requires-Dist: pywin32 ==306
Requires-Dist: pywin32-ctypes ==0.2.2
Requires-Dist: ratelim ==0.1.6
Requires-Dist: requests ==2.31.0
Requires-Dist: setuptools ==69.2.0
Requires-Dist: six ==1.16.0
Requires-Dist: tkintermapview ==1.29
Requires-Dist: urllib3 ==2.2.1
Requires-Dist: wheel ==0.43.0
